VBMicrolensing/__init__.py
VBMicrolensing/data/ESPL.tbl
VBMicrolensing/data/OB151212coords.txt
VBMicrolensing/data/satellite1.txt
VBMicrolensing/data/satellite2.txt
VBMicrolensing/data/SunEphemeris.txt
VBMicrolensing/lib/python_bindings.cpp
VBMicrolensing/lib/VBMicrolensingLibrary.cpp
VBMicrolensing/lib/VBMicrolensingLibrary.h
VBMicrolensing/VBMicrolensing.pyd
vbmicrolensing-5.3.5.dist-info/METADATA
vbmicrolensing-5.3.5.dist-info/WHEEL
vbmicrolensing-5.3.5.dist-info/licenses/LICENSE
vbmicrolensing-5.3.5.dist-info/RECORD
