Metadata-Version: 2.1
Name: VBMicrolensing
Version: 5.3.5
Summary: VBMicrolensing is a tool for efficient computation in gravitational microlensing events using the advanced contour integration method, supporting single, binary and multiple lenses.
Keywords: Microlensing magnification and astrometry
Author-Email: Valerio Bozza <valboz@sa.infn.it>, Vito Saggese <vitosaggese.vs@gmail.com>
License: LGPL-3.0
Classifier: Development Status :: 5 - Production/Stable
Classifier: Intended Audience :: Science/Research
Classifier: License :: OSI Approved :: GNU Lesser General Public License v3 (LGPLv3)
Classifier: Programming Language :: Python :: 3
Project-URL: Homepage, https://github.com/valboz/VBMicrolensing
Requires-Python: <4,>=3.7
Requires-Dist: numpy
Requires-Dist: pytest
